{
  "date": "2026-02-24",
  "videos": [
    {
      "id": "f032023cfa88e84ce8a7866baaf87aa1c8d7c97fe5f01366461182b1929b887f",
      "title": "那些GitHub上的奇怪项目，第八期",
      "url": "https://www.bilibili.com/video/BV1qgcLzREu8",
      "source": "果核次元",
      "published_at": "2026-02-13 10:50:24",
      "score": 1.0,
      "github_refs": []
    },
    {
      "id": "c3dfd0b8a9fe2a5cf5b09cc821dcaa19b0569377baf3b3a33d1c706d1cdd73bc",
      "title": "盘点4款好用到爆炸的GitHub开源软件!简直电脑装机必备!",
      "url": "https://www.bilibili.com/video/BV1czFzzFEgv",
      "source": "TechTeam软件分享",
      "published_at": "2026-02-06 12:08:35",
      "score": 2.0,
      "github_refs": []
    },
    {
      "id": "7b5354c42ed0f67340c369a0d49724512d4d123f1667d67ed474856be52403b5",
      "title": "这个AI太屌了!集成Nano Banana动动手指就能做3D建模!小白也能玩转!",
      "url": "https://www.bilibili.com/video/BV1QqzYBCEYi",
      "source": "TechTeam软件分享",
      "published_at": "2026-01-26 15:39:47",
      "score": 1.0,
      "github_refs": []
    },
    {
      "id": "15f4b4cb0d275e6e3ec0ece65403cd52f64394ae7c355f3b60d1b282242b78b0",
      "title": "盘点4款99%的人用过都说无敌的GitHub开源软件!因为它连微信都敢搞!",
      "url": "https://www.bilibili.com/video/BV1mrruB6EqS",
      "source": "TechTeam软件分享",
      "published_at": "2026-01-10 11:25:00",
      "score": 2.0,
      "github_refs": []
    },
    {
      "id": "80190b7ae7a6097afaaf436d5f33e753d8383d40085a121a3907d442203ab768",
      "title": "盘点4款UP珍藏压箱底的GitHub开源项目!全是精华极品",
      "url": "https://www.bilibili.com/video/BV1MNB4BEEab",
      "source": "TechTeam软件分享",
      "published_at": "2025-12-23 10:15:00",
      "score": 2.0,
      "github_refs": []
    }
  ]
}